directory_manager_AP/__init__.py
directory_manager_AP/core.py
directory_manager_AP/logger.py
directory_manager_ap-0.1.3.dist-info/licenses/LICENSE
directory_manager_ap-0.1.3.dist-info/METADATA
directory_manager_ap-0.1.3.dist-info/WHEEL
directory_manager_ap-0.1.3.dist-info/top_level.txt
directory_manager_ap-0.1.3.dist-info/RECORD
