Metadata-Version: 2.4
Name: directory-manager-AP
Version: 0.1.3
Summary: Универсальный инструмент для работы с директориями и файлами
Author: Александр
Author-email: sanyapetrooo@gmail.com
License: MIT
Classifier: Programming Language :: Python :: 3
Classifier: License :: OSI Approved :: MIT License
Classifier: Operating System :: OS Independent
Requires-Python: >=3.8
License-File: LICENSE
Dynamic: author
Dynamic: author-email
Dynamic: classifier
Dynamic: description
Dynamic: description-content-type
Dynamic: license
Dynamic: license-file
Dynamic: requires-python
Dynamic: summary
